{"val_loss": 8.209887608885765, "training_loss": 0.16284518454756056, "val_accuracy": 0.7410071942446043, "timestamp": 1754138725, "checkpoint_dir_name": null, "done": false, "training_iteration": 1, "trial_id": "9b255_00006", "date": "2025-08-02_14-45-25", "time_this_iter_s": 835.8728578090668, "time_total_s": 835.8728578090668, "pid": 85220, "hostname": "Bevans-MacBook-Pro.local", "node_ip": "127.0.0.1", "config": {"lr": 0.004622589001020831, "optimizer_class": "<class 'torch.optim.adam.Adam'>", "model_class": "<class 'models.classification_model.ClassificationModel'>", "criterion_class": "<class 'torch.nn.modules.loss.CrossEntropyLoss'>", "dataset": "MiraBest", "batch_size": 16}, "time_since_restore": 835.8728578090668, "iterations_since_restore": 1}
