{"val_loss": 12.556324541568756, "training_loss": 0.6931822546890803, "val_accuracy": 0.5179856115107914, "timestamp": 1753535642, "checkpoint_dir_name": null, "done": false, "training_iteration": 1, "trial_id": "9b86d_00007", "date": "2025-07-26_15-14-02", "time_this_iter_s": 765.0002429485321, "time_total_s": 765.0002429485321, "pid": 56779, "hostname": "Mac", "node_ip": "127.0.0.1", "config": {"lr": 0.021042363388306503, "optimizer_class": "<class 'torch.optim.adam.Adam'>", "model_class": "<class 'models.classification_model.ClassificationModel'>", "criterion_class": "<class 'torch.nn.modules.loss.CrossEntropyLoss'>", "dataset": "MiraBest", "batch_size": 8}, "time_since_restore": 765.0002429485321, "iterations_since_restore": 1}
